packageit/PackageIt.ini
packageit/README_body.rst
packageit/__init__.py
packageit/packageit.py
packageit-3.4.0.dist-info/LICENSE
packageit-3.4.0.dist-info/METADATA
packageit-3.4.0.dist-info/WHEEL
packageit-3.4.0.dist-info/RECORD
