Metadata-Version: 2.3
Name: PackageIt
Version: 3.4.0
Summary: Create new, build and install Python Packages from a template
License: MIT
Author: Hendrik du Toit
Author-email: hendrik@brightedge.co.za
Maintainer: Hendrik du Toit
Maintainer-email: hendrikdt@citiqprepaid.co.za
Requires-Python: >=3.10
Classifier: Development Status :: 3 - Alpha
Classifier: Intended Audience :: Developers
Classifier: Topic :: Software Development
Classifier: Topic :: Software Development
Classifier: Topic :: Software Development :: Version Control
Classifier: Topic :: Software Development :: Version Control :: Git
Classifier: License :: OSI Approved :: MIT License
Classifier: Programming Language :: Python :: 3.10
Classifier: Programming Language :: Python :: 3.11
Classifier: Programming Language :: Python :: 3.12
Requires-Dist: beetools (>=5.2.4,<6.0.0)
Requires-Dist: configparserext (>=1.4.8,<2.0.0)
Requires-Dist: gitignore-parser (>=0.1.11,<0.2.0)
Requires-Dist: gitpython (>=3.1.44,<4.0.0)
Requires-Dist: pydantic-settings (>=2.7.1,<3.0.0)
Requires-Dist: pygithub (>=2.5.0,<3.0.0)
Requires-Dist: releaselogit (>=0.17.0,<1.0.0)
Requires-Dist: semverit (>=0.3.9,<1.0.0)
Requires-Dist: setuptools (>=75.8.0,<76.0.0)
Requires-Dist: toml (>=0.10.2,<0.11.0)
Project-URL: Homepage, https://github.com/BrightEdgeeServices/PackageIt
Project-URL: Repository, https://github.com/BrightEdgeeServices/PackageIt.git
Project-URL: changelog, https://github.com/BrightEdgeeServices/PackageIt/blob/enhancement/master/ReleaseNotes.md
Project-URL: issues, https://github.com/BrightEdgeeServices/PackageIt/issues
